unirna/__init__.py
unirna/_version.py
unirna/config.py
unirna/convert.py
unirna/model.py
unirna/tokenizer.py
unirna/template/special_tokens_map.json
unirna/template/tokenizer_config.json
unirna/template/vocab.txt
unirna-0.0.1.dist-info/METADATA
unirna-0.0.1.dist-info/WHEEL
unirna-0.0.1.dist-info/top_level.txt
unirna-0.0.1.dist-info/RECORD
