Metadata-Version: 2.1
Name: unirna
Version: 0.0.1
Summary: The Large-Scale Pre-Trained Model for RNA
Author-email: Zhiyuan Chen <chenzhiyuan@dp.tech>
Maintainer-email: Zhiyuan Chen <chenzhiyuan@dp.tech>
Project-URL: homepage, http://git.dp.tech/macromolecule/unirna_transformers
Project-URL: repository, http://git.dp.tech/macromolecule/unirna_transformers
Project-URL: documentation, http://git.dp.tech/macromolecule/unirna_transformers
Keywords: Machine Learning,Transformers,UniRNA,RNA
Classifier: Development Status :: 5 - Production/Stable
Classifier: Intended Audience :: Developers
Classifier: Intended Audience :: Education
Classifier: Intended Audience :: Science/Research
Classifier: Operating System :: OS Independent
Classifier: Topic :: Scientific/Engineering :: Artificial Intelligence
Requires-Python: >=3
Requires-Dist: chanfig (>0.0.55)
